FerhassioSaver.py
__init__.py
FerhassioSaver-1.0.7.dist-info/LICENSE
FerhassioSaver-1.0.7.dist-info/METADATA
FerhassioSaver-1.0.7.dist-info/WHEEL
FerhassioSaver-1.0.7.dist-info/top_level.txt
FerhassioSaver-1.0.7.dist-info/RECORD
