Metadata-Version: 2.1
Name: FerhassioSaver
Version: 1.0.7
Summary: Python-arango wrapper
Author-email: Ferhassio <ferhassio@gmail.com>
Classifier: Programming Language :: Python :: 3
Classifier: License :: OSI Approved :: MIT License
Classifier: Operating System :: OS Independent
Requires-Python: >=3.9
License-File: LICENSE
